kryptoflow/__init__.py
kryptoflow/main.py
kryptoflow/api/__init__.py
kryptoflow/api/test.py
kryptoflow/api/utils.py
kryptoflow/api/endpoints/__init__.py
kryptoflow/api/endpoints/historic.py
kryptoflow/api/endpoints/live.py
kryptoflow/api/endpoints/predict.py
kryptoflow/api/endpoints/ws.py
kryptoflow/api/helpers/__init__.py
kryptoflow/api/helpers/tf_serving_client.py
kryptoflow/api/tensorflow_serving/__init__.py
kryptoflow/cli/__init__.py
kryptoflow/cli/dashboard.py
kryptoflow/cli/init.py
kryptoflow/cli/scrape.py
kryptoflow/cli/serve.py
kryptoflow/cli/train.py
kryptoflow/cli/version.py
kryptoflow/common/__init__.py
kryptoflow/common/data_interface.py
kryptoflow/common/observers.py
kryptoflow/common/supervisor_client.py
kryptoflow/common/utils.py
kryptoflow/common/validation.py
kryptoflow/managers/__init__.py
kryptoflow/managers/app_config.py
kryptoflow/managers/base.py
kryptoflow/managers/constants.py
kryptoflow/managers/dashboard.py
kryptoflow/managers/data.py
kryptoflow/managers/project.py
kryptoflow/managers/resource.py
kryptoflow/managers/secrets.py
kryptoflow/ml/__init__.py
kryptoflow/ml/dataset.py
kryptoflow/ml/labeling.py
kryptoflow/ml/model.py
kryptoflow/models/__init__.py
kryptoflow/models/conf.py
kryptoflow/models/model.py
kryptoflow/scrapers/__init__.py
kryptoflow/scrapers/gdax_ws.py
kryptoflow/scrapers/reddit.py
kryptoflow/scrapers/twitter.py
kryptoflow/scrapers/transforms/__init__.py
kryptoflow/scrapers/transforms/sent_analysis.py
kryptoflow/template/.gitignore
kryptoflow/template/Dockerfile
kryptoflow/template/Dockerfile.tfserving
kryptoflow/template/__init__.py
kryptoflow/template/docker-compose.yaml
kryptoflow/template/kryptoflow.yaml
kryptoflow/template/model.py
kryptoflow/template/secrets.yaml
kryptoflow/template/kafka/count_messages.sh
kryptoflow/template/kafka/server.properties
kryptoflow/template/kafka/set_topics_config.sh
kryptoflow/template/kafka/logs/.gitkeep
kryptoflow/template/kafka/schemas/gdax.avsc
kryptoflow-0.5.1.dist-info/LICENSE.txt
kryptoflow-0.5.1.dist-info/METADATA
kryptoflow-0.5.1.dist-info/WHEEL
kryptoflow-0.5.1.dist-info/dependency_links.txt
kryptoflow-0.5.1.dist-info/entry_points.txt
kryptoflow-0.5.1.dist-info/top_level.txt
kryptoflow-0.5.1.dist-info/RECORD
