Metadata-Version: 2.1
Name: kryptoflow
Version: 0.5.1
Summary: Add a short description here!
Home-page: https://carlomazzaferro.github.io/kryptoflow/
Author: Carlo Mazzaferro
Author-email: carlo.mazzaferro@gmail.com
License: mit
Keywords: kryptoflow,tensorFlow,deep-learning,machine-learning,data-science,bitcoin,kafka,time-series
Platform: any
Classifier: Programming Language :: Python
Classifier: Operating System :: OS Independent
Classifier: Intended Audience :: Developers
Classifier: Intended Audience :: Science/Research
Classifier: Topic :: Scientific/Engineering :: Artificial Intelligence
Requires-Dist: numpy (>=1.13.3)
Requires-Dist: scipy (==1.1.0)
Requires-Dist: h5py
Requires-Dist: confluent-kafka
Requires-Dist: joblib
Requires-Dist: pyyaml
Requires-Dist: avro-python3
Requires-Dist: scikit-learn
Requires-Dist: sortedcontainers
Requires-Dist: kafka-tfrx
Requires-Dist: Flask (>=1.0)
Requires-Dist: flask-restplus (==0.10.1)
Requires-Dist: flask-cors
Requires-Dist: Flask-SocketIO (==3.0.0)
Requires-Dist: docker
Requires-Dist: rx
Requires-Dist: six (>=1.11.0)
Requires-Dist: supervisor (==4.0.0.dev0)
Provides-Extra: aws
Requires-Dist: boto3 (==1.7.81); extra == 'aws'
Provides-Extra: nlp
Requires-Dist: nltk; extra == 'nlp'
Requires-Dist: tweet-preprocessor; extra == 'nlp'
Requires-Dist: tweepy; extra == 'nlp'
Requires-Dist: praw; extra == 'nlp'
Provides-Extra: test
Requires-Dist: pytest (==3.6.1); extra == 'test'
Requires-Dist: pytest-cov (==2.5.1); extra == 'test'
Requires-Dist: pytest-runner (==4.2); extra == 'test'
Requires-Dist: python-coveralls (==2.9.1); extra == 'test'
Provides-Extra: tf
Requires-Dist: tensorflow (==1.10.0); extra == 'tf'
Provides-Extra: tf_gpu
Requires-Dist: tensorflow-gpu (==1.10.0); extra == 'tf_gpu'
